ds18b20S/__init__.py
ds18b20S-0.0.1.dist-info/LICENSE
ds18b20S-0.0.1.dist-info/METADATA
ds18b20S-0.0.1.dist-info/WHEEL
ds18b20S-0.0.1.dist-info/top_level.txt
ds18b20S-0.0.1.dist-info/RECORD
